MANIFEST.in
application.py
setup.cfg
setup.py
aha.application.microneimageboard.egg-info/PKG-INFO
aha.application.microneimageboard.egg-info/SOURCES.txt
aha.application.microneimageboard.egg-info/dependency_links.txt
aha.application.microneimageboard.egg-info/entry_points.txt
aha.application.microneimageboard.egg-info/not-zip-safe
aha.application.microneimageboard.egg-info/requires.txt
aha.application.microneimageboard.egg-info/top_level.txt
asset/main.css
template/index.html