Metadata-Version: 1.0
Name: aha.application.microneimageboard
Version: 0.6bdev
Summary: An image bbs application with twitter authentication.
Home-page: http://coreblog.org/aha
Author: Atsushi Shibata
Author-email: shibata@webcore.co.jp
License: BSD
Keywords: web aha appengine web
Platform: UNKNOWN
